unwanted_content_detector/__init__.py
unwanted_content_detector/data/__init__.py
unwanted_content_detector/data/data.csv
unwanted_content_detector/data/data_loader.py
unwanted_content_detector/data/generative_prompts.txt
unwanted_content_detector/detector.py
unwanted_content_detector/entities.py
unwanted_content_detector/evaluator/evaluator.py
unwanted_content_detector/models/__init__.py
unwanted_content_detector/models/distilbert_finetuned/__init__.py
unwanted_content_detector/models/distilbert_finetuned/inference.py
unwanted_content_detector/models/distilbert_finetuned/train.py
unwanted_content_detector/models/upload.py
unwanted_content_detector-0.1.8.dist-info/METADATA
unwanted_content_detector-0.1.8.dist-info/WHEEL
unwanted_content_detector-0.1.8.dist-info/entry_points.txt
unwanted_content_detector-0.1.8.dist-info/RECORD
