Metadata-Version: 2.1
Name: unwanted-content-detector
Version: 0.1.8
Summary: A library to detect undesired, unbranded, or harmful content
License: Apache
Author: Jean Carlo Machado
Author-email: jean.machado@getyourguide.com
Requires-Python: >=3.9,<4.0
Classifier: License :: Other/Proprietary License
Classifier: Programming Language :: Python :: 3
Classifier: Programming Language :: Python :: 3.9
Classifier: Programming Language :: Python :: 3.10
Classifier: Programming Language :: Python :: 3.11
Requires-Dist: evaluate (>=0.4.0,<0.5.0)
Requires-Dist: fire (>=0.5.0,<0.6.0)
Requires-Dist: pandas (>=2.0.0,<3.0.0)
Requires-Dist: torch (>=2.0.0,<3.0.0)
Requires-Dist: transformers (>=4.28.0,<5.0.0)
